chill_compiler/__init__.py
chill_compiler/ast_nodes.py
chill_compiler/cli.py
chill_compiler/codegen.py
chill_compiler/lexer.py
chill_compiler/parser.py
chill_compiler/semantic.py
chill_compiler-1.0.0.dist-info/licenses/LICENSE
chill_compiler-1.0.0.dist-info/METADATA
chill_compiler-1.0.0.dist-info/WHEEL
chill_compiler-1.0.0.dist-info/entry_points.txt
chill_compiler-1.0.0.dist-info/top_level.txt
chill_compiler-1.0.0.dist-info/RECORD
