Metadata-Version: 2.4
Name: chill-compiler
Version: 1.0.0
Summary: CHILL to C transpiler - because GCC removed it in 2001 and someone had to do something
Author-email: Zane Hambly <zanehambly@gmail.com>
License: Apache-2.0
Project-URL: Homepage, https://github.com/Zaneham/chill-compiler
Project-URL: Repository, https://github.com/Zaneham/chill-compiler
Project-URL: Issues, https://github.com/Zaneham/chill-compiler/issues
Keywords: chill,compiler,transpiler,telecom,itu-t,z200,legacy
Classifier: Development Status :: 4 - Beta
Classifier: Environment :: Console
Classifier: Intended Audience :: Developers
Classifier: Intended Audience :: Telecommunications Industry
Classifier: License :: OSI Approved :: Apache Software License
Classifier: Operating System :: OS Independent
Classifier: Programming Language :: Python :: 3
Classifier: Programming Language :: Python :: 3.8
Classifier: Programming Language :: Python :: 3.9
Classifier: Programming Language :: Python :: 3.10
Classifier: Programming Language :: Python :: 3.11
Classifier: Programming Language :: Python :: 3.12
Classifier: Topic :: Software Development :: Compilers
Classifier: Topic :: Communications :: Telephony
Requires-Python: >=3.8
License-File: LICENSE
Dynamic: license-file
